aisa/__init__.py
aisa/base.py
aisa/utils.py
aisa-1.0.0.dist-info/LICENSE.txt
aisa-1.0.0.dist-info/METADATA
aisa-1.0.0.dist-info/WHEEL
aisa-1.0.0.dist-info/top_level.txt
aisa-1.0.0.dist-info/RECORD
