Metadata-Version: 2.1
Name: aisa
Version: 1.0.0
Summary: AISA: Auto-Information State Aggregation
Home-page: https://maurofaccin.github.io/aisa
Author: Mauro Faccin,
Author-email: mauro.fccn@gmail.com
License: GNU GPL v3+
Keywords: network,partition,state,aggregation,graph,community,detection,dynamics
Platform: UNKNOWN
Classifier: Development Status :: 4 - Beta
Classifier: Intended Audience :: End Users/Desktop
Classifier: Intended Audience :: Science/Research
Classifier: Intended Audience :: Information Technology
Classifier: Topic :: Scientific/Engineering :: Physics
Classifier: License :: OSI Approved :: GNU General Public License v3 (GPLv3)
Classifier: Operating System :: OS Independent
Classifier: Programming Language :: Python :: 3 :: Only
Classifier: Programming Language :: Python :: 3.6
Classifier: Programming Language :: Python :: 3.7
Classifier: Programming Language :: Python :: 3.8
Classifier: Programming Language :: Python :: 3.9
Requires-Dist: numpy
Requires-Dist: scipy
Requires-Dist: networkx
